termcolor_logger/__init__.py
termcolor_logger/abstract_termcolor_logger.py
termcolor_logger/colored_logger.py
termcolor_logger-1.0.3.dist-info/LICENSE
termcolor_logger-1.0.3.dist-info/METADATA
termcolor_logger-1.0.3.dist-info/WHEEL
termcolor_logger-1.0.3.dist-info/entry_points.txt
termcolor_logger-1.0.3.dist-info/top_level.txt
termcolor_logger-1.0.3.dist-info/RECORD
